vru/__init__.py
vru/example.py
vru-0.1.1.dist-info/LICENSE
vru-0.1.1.dist-info/METADATA
vru-0.1.1.dist-info/WHEEL
vru-0.1.1.dist-info/top_level.txt
vru-0.1.1.dist-info/RECORD
