Metadata-Version: 2.1
Name: vru
Version: 0.1.1
Summary: A testing package.
Home-page: https://github.com/psynx/vru/sampleproject
Author: discordians
Author-email: scratchbot@protonmail.com
License: UNKNOWN
Project-URL: Bug Tracker, https://github.com/psynx/vru/sampleproject/issues
Platform: UNKNOWN
Classifier: Programming Language :: Python :: 3
Classifier: License :: OSI Approved :: MIT License
Classifier: Operating System :: OS Independent
Requires-Python: >=3.6
